ailibrary/__init__.py
ailibrary/client.py
ailibrary/_internal/__http_client.py
ailibrary/_internal/__init__.py
ailibrary/_internal/_agent.py
ailibrary/_internal/_files.py
ailibrary/_internal/_forms.py
ailibrary/_internal/_knowledge_base.py
ailibrary/_internal/_notes.py
ailibrary/_internal/_utilities.py
ailibrary/types/__init__.py
ailibrary/types/agent/__init__.py
ailibrary/types/agent/requests.py
ailibrary/types/agent/responses.py
ailibrary/types/files/__init__.py
ailibrary/types/files/binary_file_validator.py
ailibrary/types/files/file_schema.py
ailibrary/types/files/requests.py
ailibrary/types/files/responses.py
ailibrary/types/forms/forms_base_class.py
ailibrary/types/forms/requests.py
ailibrary/types/forms/responses.py
ailibrary/types/http_client/__init__.py
ailibrary/types/http_client/http_init.py
ailibrary/types/http_client/http_request.py
ailibrary/types/http_client/responses.py
ailibrary/types/knowledge_base/__init__.py
ailibrary/types/knowledge_base/requests.py
ailibrary/types/knowledge_base/responses.py
ailibrary/types/notes/__init__.py
ailibrary/types/notes/requests.py
ailibrary/types/notes/responses.py
ailibrary/types/shared/__init__.py
ailibrary/types/shared/base.py
ailibrary/types/shared/enums.py
ailibrary/types/shared/responses.py
ailibrary/types/utilities/__init__.py
ailibrary/types/utilities/requests.py
ailibrary/types/utilities/responses.py
ailibrary-0.1.5.dist-info/METADATA
ailibrary-0.1.5.dist-info/WHEEL
ailibrary-0.1.5.dist-info/top_level.txt
ailibrary-0.1.5.dist-info/RECORD
