Metadata-Version: 2.2
Name: ailibrary
Version: 0.1.5
Summary: AI Library REST API for any Python 3.9+ application.
Author-email: Arani Chaudhuri <arani@ailibrary.ai>
Classifier: Programming Language :: Python :: 3
Classifier: Operating System :: OS Independent
Requires-Python: >=3.9
Requires-Dist: pydantic==2.10.6
Requires-Dist: Requests==2.32.3
Provides-Extra: test
Requires-Dist: pytest>=8.3.4; extra == "test"
Requires-Dist: pytest-cov; extra == "test"
Requires-Dist: pytest-mock; extra == "test"
Requires-Dist: pytest-order; extra == "test"
Requires-Dist: python-dotenv>=1.0.1; extra == "test"
Provides-Extra: dev
Requires-Dist: black; extra == "dev"
Requires-Dist: flake8; extra == "dev"
Requires-Dist: mypy; extra == "dev"
